<?xml version="1.0" ?>
<!DOCTYPE PubmedArticleSet PUBLIC "-//NLM//DTD PubMedArticle, 1st January 2024//EN" "https://dtd.nlm.nih.gov/ncbi/pubmed/out/pubmed_240101.dtd">
<PubmedArticleSet>
<PubmedArticle><MedlineCitation Status="MEDLINE" Owner="NLM" IndexingMethod="Automated"><PMID Version="1">39510792</PMID><DateCompleted><Year>2024</Year><Month>11</Month><Day>07</Day></DateCompleted><DateRevised><Year>2024</Year><Month>11</Month><Day>16</Day></DateRevised><Article PubModel="Electronic"><Journal><ISSN IssnType="Electronic">2044-6055</ISSN><JournalIssue CitedMedium="Internet"><Volume>14</Volume><Issue>11</Issue><PubDate><Year>2024</Year><Month>Nov</Month><Day>07</Day></PubDate></JournalIssue><Title>BMJ open</Title><ISOAbbreviation>BMJ Open</ISOAbbreviation></Journal><ArticleTitle>Experiences of physiotherapists working with adults living with Long COVID in Canada: a qualitative study.</ArticleTitle><Pagination><StartPage>e086357</StartPage><MedlinePgn>e086357</MedlinePgn></Pagination><ELocationID EIdType="pii" ValidYN="Y">e086357</ELocationID><ELocationID EIdType="doi" ValidYN="Y">10.1136/bmjopen-2024-086357</ELocationID><Abstract><AbstractText Label="OBJECTIVES" NlmCategory="OBJECTIVE">To explore experiences of physiotherapists working with adults living with Long COVID in Canada.</AbstractText><AbstractText Label="DESIGN" NlmCategory="METHODS">Cross-sectional descriptive qualitative study involving online semi-structured interviews.</AbstractText><AbstractText Label="PARTICIPANTS" NlmCategory="METHODS">We recruited physiotherapists in Canada who self-identified as having clinically treated one or more adults living with Long COVID in the past year.</AbstractText><AbstractText Label="DATA COLLECTION" NlmCategory="METHODS">Using an interview guide, we inquired about physiotherapists' knowledge of Long COVID, assessment and treatment experiences, perspectives on physiotherapists' roles, contextual and implementation factors influencing rehabilitative outcomes, and their recommendations for Long COVID rehabilitation. Interviews were audio-recorded, transcribed verbatim and analysed using a group-based thematic analytical approach. We administered a demographic questionnaire to describe sample characteristics.</AbstractText><AbstractText Label="RESULTS" NlmCategory="RESULTS">13 physiotherapists from five provinces participated; most were women (n=8; 62%) and practised in urban settings (n=11; 85%). Participants reported variable amounts of knowledge of existing guidelines and experiences working with adults living with Long COVID in the past year. Physiotherapists characterised their experiences working with adults living with Long COVID as a dynamic process involving: (1) a disruption to the profession (encountering a new patient population and pivoting to new models of care delivery), followed by (2) a cyclical process of learning curves and evolving roles of physiotherapists working with persons living with Long COVID (navigating uncertainty, keeping up with rapidly emerging evidence, trial and error, adapting mindset and rehabilitative approaches and growing prominence of roles as advocate and collaborator). Participants recommended the need for education and training, active and open-minded listening with patients, interdisciplinary models of care, and organisational- and system-level improvements to foster access to care.</AbstractText><AbstractText Label="CONCLUSIONS" NlmCategory="CONCLUSIONS">Physiotherapists' experiences involved a disruption to the profession followed by a dynamic process of learning curves and evolving roles in Long COVID rehabilitation. Not all participants demonstrated an in-depth understanding of existing Long COVID rehabilitation guidelines. Results may help inform physiotherapy education in Long COVID rehabilitation.</AbstractText><CopyrightInformation>&#xa9; Author(s) (or their employer(s)) 2024. Re-use permitted under CC BY-NC. No commercial re-use. See rights and permissions. Published by BMJ.</CopyrightInformation></Abstract><AuthorList CompleteYN="Y"><Author ValidYN="Y" EqualContrib="Y"><LastName>Kim</LastName><ForeName>Caleb</ForeName><Initials>C</Initials><AffiliationInfo><Affiliation>Department of Physical Therapy, Temerty Faculty of Medicine, University of Toronto, Toronto, Ontario, Canada.</Affiliation></AffiliationInfo></Author><Author ValidYN="Y" EqualContrib="Y"><LastName>Lin</LastName><ForeName>Chantal</ForeName><Initials>C</Initials><AffiliationInfo><Affiliation>Department of Physical Therapy, Temerty Faculty of Medicine, University of Toronto, Toronto, Ontario, Canada.</Affiliation></AffiliationInfo></Author><Author ValidYN="Y" EqualContrib="Y"><LastName>Wong</LastName><ForeName>Michelle</ForeName><Initials>M</Initials><Identifier Source="ORCID">0000-0001-6402-1132</Identifier><AffiliationInfo><Affiliation>Department of Physical Therapy, Temerty Faculty of Medicine, University of Toronto, Toronto, Ontario, Canada.</Affiliation></AffiliationInfo></Author><Author ValidYN="Y"><LastName>Al Hamour Al Jarad</LastName><ForeName>Shahd</ForeName><Initials>S</Initials><AffiliationInfo><Affiliation>Department of Physical Therapy, Temerty Faculty of Medicine, University of Toronto, Toronto, Ontario, Canada.</Affiliation></AffiliationInfo></Author><Author ValidYN="Y"><LastName>Gao</LastName><ForeName>Amy</ForeName><Initials>A</Initials><AffiliationInfo><Affiliation>Department of Physical Therapy, Temerty Faculty of Medicine, University of Toronto, Toronto, Ontario, Canada.</Affiliation></AffiliationInfo></Author><Author ValidYN="Y"><LastName>Kaufman</LastName><ForeName>Nicole</ForeName><Initials>N</Initials><AffiliationInfo><Affiliation>Department of Physical Therapy, Temerty Faculty of Medicine, University of Toronto, Toronto, Ontario, Canada.</Affiliation></AffiliationInfo></Author><Author ValidYN="Y"><LastName>McDuff</LastName><ForeName>Kiera</ForeName><Initials>K</Initials><Identifier Source="ORCID">0000-0003-0331-6919</Identifier><AffiliationInfo><Affiliation>Department of Physical Therapy, Temerty Faculty of Medicine, University of Toronto, Toronto, Ontario, Canada.</Affiliation></AffiliationInfo></Author><Author ValidYN="Y"><LastName>Brown</LastName><ForeName>Darren A</ForeName><Initials>DA</Initials><Identifier Source="ORCID">0000-0002-4956-243X</Identifier><AffiliationInfo><Affiliation>Long COVID Physio, London, UK.</Affiliation></AffiliationInfo><AffiliationInfo><Affiliation>Therapies Department, Chelsea and Westminster Hospital NHS Foundation Trust, London, UK.</Affiliation></AffiliationInfo></Author><Author ValidYN="Y"><LastName>Cobbing</LastName><ForeName>Saul</ForeName><Initials>S</Initials><Identifier Source="ORCID">0000-0002-0620-0658</Identifier><AffiliationInfo><Affiliation>Department of Physical Therapy, Temerty Faculty of Medicine, University of Toronto, Toronto, Ontario, Canada.</Affiliation></AffiliationInfo><AffiliationInfo><Affiliation>Physiotherapy, University of KwaZulu-Natal, Durban, South Africa.</Affiliation></AffiliationInfo></Author><Author ValidYN="Y"><LastName>Minor</LastName><ForeName>Alyssa</ForeName><Initials>A</Initials><AffiliationInfo><Affiliation>Long COVID Physio, Calgary, Alberta, Canada.</Affiliation></AffiliationInfo></Author><Author ValidYN="Y"><LastName>Chan Carusone</LastName><ForeName>Soo</ForeName><Initials>S</Initials><Identifier Source="ORCID">0000-0003-3977-0523</Identifier><AffiliationInfo><Affiliation>Collaborative for Health and Aging, McMaster University, Hamilton, Ontario, Canada.</Affiliation></AffiliationInfo></Author><Author ValidYN="Y"><LastName>O'Brien</LastName><ForeName>Kelly K</ForeName><Initials>KK</Initials><Identifier Source="ORCID">0000-0002-1632-6537</Identifier><AffiliationInfo><Affiliation>Department of Physical Therapy, Temerty Faculty of Medicine, University of Toronto, Toronto, Ontario, Canada kelly.obrien@utoronto.ca.</Affiliation></AffiliationInfo><AffiliationInfo><Affiliation>Institute of Health Policy, Management and Evaluation (IHPME), Dalla Lana School of Public Health, University of Toronto, Toronto, Ontario, Canada.</Affiliation></AffiliationInfo><AffiliationInfo><Affiliation>Rehabilitation Science Research Network for COVID, Temerty Faculty of Medicine, University of Toronto, Toronto, Ontario, Canada.</Affiliation></AffiliationInfo></Author></AuthorList><Language>eng</Language><PublicationTypeList><PublicationType UI="D016428">Journal Article</PublicationType></PublicationTypeList><ArticleDate DateType="Electronic"><Year>2024</Year><Month>11</Month><Day>07</Day></ArticleDate></Article><MedlineJournalInfo><Country>England</Country><MedlineTA>BMJ Open</MedlineTA><NlmUniqueID>101552874</NlmUniqueID><ISSNLinking>2044-6055</ISSNLinking></MedlineJournalInfo><CitationSubset>IM</CitationSubset><MeshHeadingList><MeshHeading><DescriptorName UI="D006801" MajorTopicYN="N">Humans</DescriptorName></MeshHeading><MeshHeading><DescriptorName UI="D000086382" MajorTopicYN="Y">COVID-19</DescriptorName><QualifierName UI="Q000453" MajorTopicYN="N">epidemiology</QualifierName></MeshHeading><MeshHeading><DescriptorName UI="D005260" MajorTopicYN="N">Female</DescriptorName></MeshHeading><MeshHeading><DescriptorName UI="D059825" MajorTopicYN="Y">Physical Therapists</DescriptorName></MeshHeading><MeshHeading><DescriptorName UI="D036301" MajorTopicYN="Y">Qualitative Research</DescriptorName></MeshHeading><MeshHeading><DescriptorName UI="D008297" MajorTopicYN="N">Male</DescriptorName></MeshHeading><MeshHeading><DescriptorName UI="D003430" MajorTopicYN="N">Cross-Sectional Studies</DescriptorName></MeshHeading><MeshHeading><DescriptorName UI="D002170" MajorTopicYN="N" Type="Geographic">Canada</DescriptorName></MeshHeading><MeshHeading><DescriptorName UI="D000328" MajorTopicYN="N">Adult</DescriptorName></MeshHeading><MeshHeading><DescriptorName UI="D000086402" MajorTopicYN="N">SARS-CoV-2</DescriptorName></MeshHeading><MeshHeading><DescriptorName UI="D008875" MajorTopicYN="N">Middle Aged</DescriptorName></MeshHeading><MeshHeading><DescriptorName UI="D001291" MajorTopicYN="N">Attitude of Health Personnel</DescriptorName></MeshHeading><MeshHeading><DescriptorName UI="D007722" MajorTopicYN="N">Health Knowledge, Attitudes, Practice</DescriptorName></MeshHeading></MeshHeadingList><KeywordList Owner="NOTNLM"><Keyword MajorTopicYN="N">Post-Acute COVID-19 Syndrome</Keyword><Keyword MajorTopicYN="N">QUALITATIVE RESEARCH</Keyword><Keyword MajorTopicYN="N">REHABILITATION MEDICINE</Keyword></KeywordList><CoiStatement>Competing interests: None declared.</CoiStatement></MedlineCitation><PubmedData><History><PubMedPubDate PubStatus="medline"><Year>2024</Year><Month>11</Month><Day>13</Day><Hour>13</Hour><Minute>56</Minute></PubMedPubDate><PubMedPubDate PubStatus="pubmed"><Year>2024</Year><Month>11</Month><Day>13</Day><Hour>13</Hour><Minute>55</Minute></PubMedPubDate><PubMedPubDate PubStatus="entrez"><Year>2024</Year><Month>11</Month><Day>7</Day><Hour>21</Hour><Minute>4</Minute></PubMedPubDate><PubMedPubDate PubStatus="pmc-release"><Year>2024</Year><Month>11</Month><Day>7</Day></PubMedPubDate></History><PublicationStatus>epublish</PublicationStatus><ArticleIdList><ArticleId IdType="pubmed">39510792</ArticleId><ArticleId IdType="pmc">PMC11552558</ArticleId><ArticleId IdType="doi">10.1136/bmjopen-2024-086357</ArticleId><ArticleId IdType="pii">bmjopen-2024-086357</ArticleId></ArticleIdList><ReferenceList><Reference><Citation>Callard F, Perego E. How and why patients made Long Covid. Soc Sci Med. 2021;268:113426. doi: 10.1016/j.socscimed.2020.113426.</Citation><ArticleIdList><ArticleId IdType="doi">10.1016/j.socscimed.2020.113426</ArticleId><ArticleId IdType="pmc">PMC7539940</ArticleId><ArticleId IdType="pubmed">33199035</ArticleId></ArticleIdList></Reference><Reference><Citation>Perego E, Callard F, Stras L, et al. Why the Patient-Made Term &#x201c;Long Covid&#x201d; is needed. Wellcome Open Res. 2020;5:224. doi: 10.12688/wellcomeopenres.16307.1.</Citation><ArticleIdList><ArticleId IdType="doi">10.12688/wellcomeopenres.16307.1</ArticleId></ArticleIdList></Reference><Reference><Citation>Soriano JB, Murthy S, Marshall JC, et al. A clinical case definition of post-COVID-19 condition by a Delphi consensus. Lancet Infect Dis. 2022;22:e102&#x2013;7. doi: 10.1016/S1473-3099(21)00703-9.</Citation><ArticleIdList><ArticleId IdType="doi">10.1016/S1473-3099(21)00703-9</ArticleId><ArticleId IdType="pmc">PMC8691845</ArticleId><ArticleId IdType="pubmed">34951953</ArticleId></ArticleIdList></Reference><Reference><Citation>Al-Aly Z, Davis H, McCorkell L, et al. Long COVID science, research and policy. Nat Med. 2024;30:2148&#x2013;64. doi: 10.1038/s41591-024-03173-6.</Citation><ArticleIdList><ArticleId IdType="doi">10.1038/s41591-024-03173-6</ArticleId><ArticleId IdType="pubmed">39122965</ArticleId></ArticleIdList></Reference><Reference><Citation>Kuang S, Earl S, Clarke J, et al.  Experiences of Canadians with long-term symptoms following COVID-19. 2023. https://www150.statcan.gc.ca/n1/pub/75-006-x/2023001/article/00015-eng.htm Available.</Citation></Reference><Reference><Citation>Brown DA, O&#x2019;Brien KK. Conceptualising Long COVID as an episodic health condition. BMJ Glob Health. 2021;6:e007004. doi: 10.1136/bmjgh-2021-007004.</Citation><ArticleIdList><ArticleId IdType="doi">10.1136/bmjgh-2021-007004</ArticleId><ArticleId IdType="pmc">PMC8460526</ArticleId><ArticleId IdType="pubmed">34551971</ArticleId></ArticleIdList></Reference><Reference><Citation>O&#x2019;Brien KK, Brown DA, McDuff K, et al. Conceptualising the episodic nature of disability among adults living with Long COVID: a qualitative study. BMJ Glob Health. 2023;8:e011276. doi: 10.1136/bmjgh-2022-011276.</Citation><ArticleIdList><ArticleId IdType="doi">10.1136/bmjgh-2022-011276</ArticleId><ArticleId IdType="pmc">PMC9979585</ArticleId><ArticleId IdType="pubmed">36863719</ArticleId></ArticleIdList></Reference><Reference><Citation>Davis HE, McCorkell L, Vogel JM, et al. Long COVID: major findings, mechanisms and recommendations. Nat Rev Microbiol. 2023;21:133&#x2013;46. doi: 10.1038/s41579-022-00846-2.</Citation><ArticleIdList><ArticleId IdType="doi">10.1038/s41579-022-00846-2</ArticleId><ArticleId IdType="pmc">PMC9839201</ArticleId><ArticleId IdType="pubmed">36639608</ArticleId></ArticleIdList></Reference><Reference><Citation>O&#x2019;Mahoney LL, Routen A, Gillies C, et al. The prevalence and long-term health effects of Long Covid among hospitalised and non-hospitalised populations: A systematic review and meta-analysis. E Clin Med. 2023;55:101762. doi: 10.1016/j.eclinm.2022.101762.</Citation><ArticleIdList><ArticleId IdType="doi">10.1016/j.eclinm.2022.101762</ArticleId><ArticleId IdType="pmc">PMC9714474</ArticleId><ArticleId IdType="pubmed">36474804</ArticleId></ArticleIdList></Reference><Reference><Citation>Davis HE, Assaf GS, McCorkell L, et al. Characterizing Long COVID in an international cohort: 7 months of symptoms and their impact. EClinMed. 2021;38:101019. doi: 10.1016/j.eclinm.2021.101019.</Citation><ArticleIdList><ArticleId IdType="doi">10.1016/j.eclinm.2021.101019</ArticleId><ArticleId IdType="pmc">PMC8280690</ArticleId><ArticleId IdType="pubmed">34308300</ArticleId></ArticleIdList></Reference><Reference><Citation>Torrell G, Puente D, Jacques-Avi&#xf1;&#xf3; C, et al. Characterisation, symptom pattern and symptom clusters from a retrospective cohort of Long COVID patients in primary care in Catalonia. BMC Infect Dis. 2024;24:82. doi: 10.1186/s12879-023-08954-x.</Citation><ArticleIdList><ArticleId IdType="doi">10.1186/s12879-023-08954-x</ArticleId><ArticleId IdType="pmc">PMC10789045</ArticleId><ArticleId IdType="pubmed">38225587</ArticleId></ArticleIdList></Reference><Reference><Citation>National Institute for Health and Care Excellence (NICE) Myalgic encephalomyelitis (or encephalopathy)/chronic fatigue syndrome: diagnosis and management. 2021.</Citation><ArticleIdList><ArticleId IdType="pubmed">35438861</ArticleId></ArticleIdList></Reference><Reference><Citation>Wong TL, Weitzer DJ. Long COVID and Myalgic Encephalomyelitis/Chronic Fatigue Syndrome (ME/CFS)-A Systemic Review and Comparison of Clinical Presentation and Symptomatology. Medicina (Kaunas) 2021;57:418. doi: 10.3390/medicina57050418.</Citation><ArticleIdList><ArticleId IdType="doi">10.3390/medicina57050418</ArticleId><ArticleId IdType="pmc">PMC8145228</ArticleId><ArticleId IdType="pubmed">33925784</ArticleId></ArticleIdList></Reference><Reference><Citation>Twomey R, DeMars J, Franklin K, et al. Chronic Fatigue and Postexertional Malaise in People Living With Long COVID: An Observational Study. Phys Ther. 2022;102:pzac005. doi: 10.1093/ptj/pzac005.</Citation><ArticleIdList><ArticleId IdType="doi">10.1093/ptj/pzac005</ArticleId><ArticleId IdType="pmc">PMC9383197</ArticleId><ArticleId IdType="pubmed">35079817</ArticleId></ArticleIdList></Reference><Reference><Citation>Thaweethai T, Jolley SE, Karlson EW, et al. Development of a Definition of Postacute Sequelae of SARS-CoV-2 Infection. JAMA. 2023;329:1934&#x2013;46. doi: 10.1001/jama.2023.8823.</Citation><ArticleIdList><ArticleId IdType="doi">10.1001/jama.2023.8823</ArticleId><ArticleId IdType="pmc">PMC10214179</ArticleId><ArticleId IdType="pubmed">37278994</ArticleId></ArticleIdList></Reference><Reference><Citation>Wasilewski MB, Cimino SR, Kokorelias KM, et al. Providing rehabilitation to patients recovering from COVID-19: A scoping review. PM R. 2022;14:239&#x2013;58. doi: 10.1002/pmrj.12669.</Citation><ArticleIdList><ArticleId IdType="doi">10.1002/pmrj.12669</ArticleId><ArticleId IdType="pmc">PMC8441670</ArticleId><ArticleId IdType="pubmed">34240576</ArticleId></ArticleIdList></Reference><Reference><Citation>Chuang H-J, Lin C-W, Hsiao M-Y, et al. Long COVID and rehabilitation. J Formos Med Assoc. 2024;123:S61&#x2013;9. doi: 10.1016/j.jfma.2023.03.022.</Citation><ArticleIdList><ArticleId IdType="doi">10.1016/j.jfma.2023.03.022</ArticleId><ArticleId IdType="pmc">PMC10101546</ArticleId><ArticleId IdType="pubmed">37061399</ArticleId></ArticleIdList></Reference><Reference><Citation>Canada S. Long-term symptoms in Canadian adults who tested positive for COVID-19 or suspected an infection. 2020. https://www150.statcan.gc.ca/n1/daily-quotidien/221017/dq221017b-eng.htm Available.</Citation></Reference><Reference><Citation>O&#x2019;Brien KK, Bayoumi AM, Strike C, et al. Exploring disability from the perspective of adults living with HIV/AIDS: development of a conceptual framework. Health Qual Life Outcomes. 2008;6:76. doi: 10.1186/1477-7525-6-76.</Citation><ArticleIdList><ArticleId IdType="doi">10.1186/1477-7525-6-76</ArticleId><ArticleId IdType="pmc">PMC2572592</ArticleId><ArticleId IdType="pubmed">18834538</ArticleId></ArticleIdList></Reference><Reference><Citation>O&#x2019;Brien KK, Brown DA, Bergin C, et al. Long COVID and episodic disability: advancing the conceptualisation, measurement and knowledge of episodic disability among people living with Long COVID - protocol for a mixed-methods study. BMJ Open. 2022;12:e060826. doi: 10.1136/bmjopen-2022-060826.</Citation><ArticleIdList><ArticleId IdType="doi">10.1136/bmjopen-2022-060826</ArticleId><ArticleId IdType="pmc">PMC8905414</ArticleId><ArticleId IdType="pubmed">35256450</ArticleId></ArticleIdList></Reference><Reference><Citation>Monteiro IP, Appelt PA, Sisconetto AT, et al. Post-coronavirus disease 2019 functional impairments, limitations, and restrictions: A prospective cohort study based on the international classification of functioning, disability, and health. J Cent Nerv Syst Dis. 2023;15:11795735231195759. doi: 10.1177/11795735231195759.</Citation><ArticleIdList><ArticleId IdType="doi">10.1177/11795735231195759</ArticleId><ArticleId IdType="pmc">PMC10655659</ArticleId><ArticleId IdType="pubmed">38025402</ArticleId></ArticleIdList></Reference><Reference><Citation>O&#x2019;Brien KK, Brown DA, McDuff K, et al. Conceptual framework of episodic disability in the context of long covid: findings from a community-engaged international qualitative study. Infectious Diseases (except HIV/AIDS) doi: 10.1101/2024.05.28.24308048. Preprint.</Citation><ArticleIdList><ArticleId IdType="doi">10.1101/2024.05.28.24308048</ArticleId></ArticleIdList></Reference><Reference><Citation>Office for National Statistics  Self-reported coronavirus (covid-19) infections and associated symptoms. 2023. https://www.ons.gov.uk/peoplepopulationandcommunity/healthandsocialcare/conditionsanddiseases/articles/selfreportedcoronaviruscovid19infectionsandassociatedsymptomsenglandandscotland/november2023tomarch2024 Available.</Citation></Reference><Reference><Citation>Perlis RH, Lunz Trujillo K, Safarpour A, et al. Association of Post-COVID-19 Condition Symptoms and Employment Status. JAMA Netw Open. 2023;6:e2256152. doi: 10.1001/jamanetworkopen.2022.56152.</Citation><ArticleIdList><ArticleId IdType="doi">10.1001/jamanetworkopen.2022.56152</ArticleId><ArticleId IdType="pmc">PMC9932847</ArticleId><ArticleId IdType="pubmed">36790806</ArticleId></ArticleIdList></Reference><Reference><Citation>Packard SE, Susser E. Association of long COVID with housing insecurity in the United States, 2022-2023. SSM Popul Health. 2024;25:101586. doi: 10.1016/j.ssmph.2023.101586.</Citation><ArticleIdList><ArticleId IdType="doi">10.1016/j.ssmph.2023.101586</ArticleId><ArticleId IdType="pmc">PMC10787291</ArticleId><ArticleId IdType="pubmed">38222672</ArticleId></ArticleIdList></Reference><Reference><Citation>Stelson EA, Dash D, McCorkell L, et al. Return-to-work with long COVID: An Episodic Disability and Total Worker Health&#xae; analysis. Soc Sci Med. 2023;338:S0277-9536(23)00693-7. doi: 10.1016/j.socscimed.2023.116336.</Citation><ArticleIdList><ArticleId IdType="doi">10.1016/j.socscimed.2023.116336</ArticleId><ArticleId IdType="pubmed">37918226</ArticleId></ArticleIdList></Reference><Reference><Citation>Voruz P, Assal F, P&#xe9;ron JA. The economic burden of the post-COVID-19 condition: Underestimated long-term consequences of neuropsychological deficits. J Glob Health. 2023;13:03019. doi: 10.7189/jogh.13.03019.</Citation><ArticleIdList><ArticleId IdType="doi">10.7189/jogh.13.03019</ArticleId><ArticleId IdType="pmc">PMC10159592</ArticleId><ArticleId IdType="pubmed">37141527</ArticleId></ArticleIdList></Reference><Reference><Citation>Cutler DM, Summers LH. The COVID-19 Pandemic and the $16 Trillion Virus. JAMA. 2020;324:1495&#x2013;6. doi: 10.1001/jama.2020.19759.</Citation><ArticleIdList><ArticleId IdType="doi">10.1001/jama.2020.19759</ArticleId><ArticleId IdType="pmc">PMC7604733</ArticleId><ArticleId IdType="pubmed">33044484</ArticleId></ArticleIdList></Reference><Reference><Citation>Cutler DM. The Costs of Long COVID. JAMA Health Forum . 2022;3:e221809. doi: 10.1001/jamahealthforum.2022.1809.</Citation><ArticleIdList><ArticleId IdType="doi">10.1001/jamahealthforum.2022.1809</ArticleId><ArticleId IdType="pubmed">36219031</ArticleId></ArticleIdList></Reference><Reference><Citation>D&#xe9;cary S, De Groote W, Arienti C, et al. Scoping review of rehabilitation care models for post COVID-19 condition. Bull World Health Organ. 2022;100:676&#x2013;88. doi: 10.2471/BLT.22.288105.</Citation><ArticleIdList><ArticleId IdType="doi">10.2471/BLT.22.288105</ArticleId><ArticleId IdType="pmc">PMC9589389</ArticleId><ArticleId IdType="pubmed">36324552</ArticleId></ArticleIdList></Reference><Reference><Citation>World Health Organization  Clinical management of COVID-19: Living guideline. 2023. https://www.who.int/publications/i/item/WHO-2019-nCoV-clinical-2023.2 Available.</Citation><ArticleIdList><ArticleId IdType="pubmed">35917394</ArticleId></ArticleIdList></Reference><Reference><Citation>DeMars J, Brown DA, Angelidis I, et al. What is Safe Long COVID Rehabilitation? J Occup Rehabil. 2023;33:227&#x2013;30. doi: 10.1007/s10926-022-10075-2.</Citation><ArticleIdList><ArticleId IdType="doi">10.1007/s10926-022-10075-2</ArticleId><ArticleId IdType="pmc">PMC9628454</ArticleId><ArticleId IdType="pubmed">36315323</ArticleId></ArticleIdList></Reference><Reference><Citation>Gloeckl R, Leitl D, Schneeberger T, et al. Rehabilitative interventions in patients with persistent post COVID-19 symptoms-a review of recent advances and future perspectives. Eur Arch Psychiatry Clin Neurosci. 2023 doi: 10.1007/s00406-023-01631-9.</Citation><ArticleIdList><ArticleId IdType="doi">10.1007/s00406-023-01631-9</ArticleId><ArticleId IdType="pubmed">37326700</ArticleId></ArticleIdList></Reference><Reference><Citation>Romanet C, Wormser J, Fels A, et al. Effectiveness of exercise training on the dyspnoea of individuals with long COVID: A randomised controlled multicentre trial. Ann Phys Rehabil Med. 2023;66:S1877-0657(23)00036-2. doi: 10.1016/j.rehab.2023.101765.</Citation><ArticleIdList><ArticleId IdType="doi">10.1016/j.rehab.2023.101765</ArticleId><ArticleId IdType="pmc">PMC10237688</ArticleId><ArticleId IdType="pubmed">37271020</ArticleId></ArticleIdList></Reference><Reference><Citation>Michelen M, Manoharan L, Elkheir N, et al. Characterising long COVID: a living systematic review. BMJ Glob Health. 2021;6:e005427. doi: 10.1136/bmjgh-2021-005427.</Citation><ArticleIdList><ArticleId IdType="doi">10.1136/bmjgh-2021-005427</ArticleId><ArticleId IdType="pmc">PMC8478580</ArticleId><ArticleId IdType="pubmed">34580069</ArticleId></ArticleIdList></Reference><Reference><Citation>Kluge HHP, Muscat NA, Contribution from - et al. Call for action: Health services in the European region must adopt integrated care models to manage Post-Covid-19 Condition. Lancet Reg Health Eur . 2022;18:100435. doi: 10.1016/j.lanepe.2022.100435.</Citation><ArticleIdList><ArticleId IdType="doi">10.1016/j.lanepe.2022.100435</ArticleId><ArticleId IdType="pmc">PMC9217062</ArticleId><ArticleId IdType="pubmed">35756854</ArticleId></ArticleIdList></Reference><Reference><Citation>Kabir MdF, Nyein Yin K, Jeffree MS, et al. A comprehensive systematic scoping review for physiotherapy interventions for people living with long COVID. F1000Res. 2023;12:368. doi: 10.12688/f1000research.132098.2.</Citation><ArticleIdList><ArticleId IdType="doi">10.12688/f1000research.132098.2</ArticleId></ArticleIdList></Reference><Reference><Citation>Spruit MA, Holland AE, Singh SJ, et al. COVID-19: Interim Guidance on Rehabilitation in the Hospital and Post-Hospital Phase from a European Respiratory Society and American Thoracic Society-coordinated International Task Force. Eur Respir J. 2020;56:2002197. doi: 10.1183/13993003.02197-2020.</Citation><ArticleIdList><ArticleId IdType="doi">10.1183/13993003.02197-2020</ArticleId><ArticleId IdType="pmc">PMC7427118</ArticleId><ArticleId IdType="pubmed">32817258</ArticleId></ArticleIdList></Reference><Reference><Citation>Vitacca M, Carone M, Clini EM, et al. Joint Statement on the Role of Respiratory Rehabilitation in the COVID-19 Crisis: The Italian Position Paper. Respiration. 2020;99:493&#x2013;9. doi: 10.1159/000508399.</Citation><ArticleIdList><ArticleId IdType="doi">10.1159/000508399</ArticleId><ArticleId IdType="pmc">PMC7316664</ArticleId><ArticleId IdType="pubmed">32428909</ArticleId></ArticleIdList></Reference><Reference><Citation>Physiotherapy W. World Physiotherapy response to COVID-19. Safe rehabilitation approaches for people living with Long COVID: physical activity and exercise. 2021. https://world.physio/sites/default/files/2021-07/Briefing-Paper-9-Long-Covid-FINAL-English-202107.pdf Available.</Citation></Reference><Reference><Citation>Sandelowski M. Whatever happened to qualitative description? Res Nurs Health. 2000;23:334&#x2013;40. doi: 10.1002/1098-240x(200008)23:4&lt;334::aid-nur9&gt;3.0.co;2-g.</Citation><ArticleIdList><ArticleId IdType="doi">10.1002/1098-240x(200008)23:4&lt;334::aid-nur9&gt;3.0.co;2-g</ArticleId><ArticleId IdType="pubmed">10940958</ArticleId></ArticleIdList></Reference><Reference><Citation>Long COVID Physio. https://lnk.bio/YUiz Available.</Citation></Reference><Reference><Citation>Palinkas LA, Horwitz SM, Green CA, et al. Purposeful Sampling for Qualitative Data Collection and Analysis in Mixed Method Implementation Research. Adm Policy Ment Health. 2015;42:533&#x2013;44. doi: 10.1007/s10488-013-0528-y.</Citation><ArticleIdList><ArticleId IdType="doi">10.1007/s10488-013-0528-y</ArticleId><ArticleId IdType="pmc">PMC4012002</ArticleId><ArticleId IdType="pubmed">24193818</ArticleId></ArticleIdList></Reference><Reference><Citation>Goodman LA. Snowball Sampling. Ann Math Statist. 1961;32:148&#x2013;70. doi: 10.1214/aoms/1177705148.</Citation><ArticleIdList><ArticleId IdType="doi">10.1214/aoms/1177705148</ArticleId></ArticleIdList></Reference><Reference><Citation>Zoom Health Care Video Communications Inc Zoom Health Care Video Communications. 2020.</Citation></Reference><Reference><Citation>Ortlipp M. Keeping and Using Reflective Journals in the Qualitative Research Process. Qual Rep. 2008;13:695&#x2013;705.</Citation></Reference><Reference><Citation>Microsoft Corporation Microsoft Word Software. 2023.</Citation></Reference><Reference><Citation>Braun V, Clarke V. Using thematic analysis in psychology. Qual Res Psychol. 2006;3:77&#x2013;101. doi: 10.1191/1478088706qp063oa.</Citation><ArticleIdList><ArticleId IdType="doi">10.1191/1478088706qp063oa</ArticleId></ArticleIdList></Reference><Reference><Citation>Flicker S, Nixon SA. The DEPICT model for participatory qualitative health promotion research analysis piloted in Canada, Zambia and South Africa. Health Promot Int . 2015;30:616&#x2013;24. doi: 10.1093/heapro/dat093.</Citation><ArticleIdList><ArticleId IdType="doi">10.1093/heapro/dat093</ArticleId><ArticleId IdType="pmc">PMC4542917</ArticleId><ArticleId IdType="pubmed">24418997</ArticleId></ArticleIdList></Reference><Reference><Citation>Microsoft Corporation Microsoft Excel. Microsoft Corporation. 2016.</Citation></Reference><Reference><Citation>Olateju Z, Olufunlayo T, MacArthur C, et al. Community health workers experiences and perceptions of working during the COVID-19 pandemic in Lagos, Nigeria-A qualitative study. PLoS One. 2022;17:e0265092. doi: 10.1371/journal.pone.0265092.</Citation><ArticleIdList><ArticleId IdType="doi">10.1371/journal.pone.0265092</ArticleId><ArticleId IdType="pmc">PMC8903241</ArticleId><ArticleId IdType="pubmed">35259204</ArticleId></ArticleIdList></Reference><Reference><Citation>Brewer E, Carnevale N, Ducsharm M, et al. Physiotherapists&#x2019; Experiences with and Perspectives on Implementing an Evidence-Based, Chronic Pain Self-Management Programme in Primary Health Care: A Qualitative Study. 2020;23</Citation><ArticleIdList><ArticleId IdType="pmc">PMC8370737</ArticleId><ArticleId IdType="pubmed">34456427</ArticleId></ArticleIdList></Reference><Reference><Citation>Li A, McCabe T, Silverstein E, et al. Community-Based Exercise in the Context of HIV. J Int Assoc Provid AIDS Care. 2017:2325957416686836</Citation><ArticleIdList><ArticleId IdType="pubmed">28074681</ArticleId></ArticleIdList></Reference><Reference><Citation>National Physiotherapy Advisory Group Competency Profile for Physiotherapists in Canada. 2017.</Citation></Reference><Reference><Citation>Curnow E, Tyagi V, Salisbury L, et al. Person-Centered Healthcare Practice in a Pandemic Context: An Exploration of People&#x2019;s Experience of Seeking Healthcare Support. Front Rehabil Sci . 2021;2:726210. doi: 10.3389/fresc.2021.726210.</Citation><ArticleIdList><ArticleId IdType="doi">10.3389/fresc.2021.726210</ArticleId><ArticleId IdType="pmc">PMC9397956</ArticleId><ArticleId IdType="pubmed">36188789</ArticleId></ArticleIdList></Reference><Reference><Citation>Russell D, Spence NJ, Chase J-AD, et al. Support amid uncertainty: Long COVID illness experiences and the role of online communities. SSM Qual Res Health . 2022;2:100177. doi: 10.1016/j.ssmqr.2022.100177.</Citation><ArticleIdList><ArticleId IdType="doi">10.1016/j.ssmqr.2022.100177</ArticleId><ArticleId IdType="pmc">PMC9531408</ArticleId><ArticleId IdType="pubmed">36212783</ArticleId></ArticleIdList></Reference><Reference><Citation>Sivan M, Parkin A, Makower S, et al. Post-COVID syndrome symptoms, functional disability, and clinical severity phenotypes in hospitalized and nonhospitalized individuals: A cross-sectional evaluation from a community COVID rehabilitation service. J Med Virol. 2022;94:1419&#x2013;27. doi: 10.1002/jmv.27456.</Citation><ArticleIdList><ArticleId IdType="doi">10.1002/jmv.27456</ArticleId><ArticleId IdType="pmc">PMC8661751</ArticleId><ArticleId IdType="pubmed">34783052</ArticleId></ArticleIdList></Reference><Reference><Citation>Chartered Institute of Personnel and Development (CIPD) Working with long COVID: Guidance for people professionals. 2022.</Citation></Reference><Reference><Citation>Cohen J, van der Meulen Rodgers Y. An intersectional analysis of Long COVID prevalence. Int J Equity Health. 2023;22:261. doi: 10.1186/s12939-023-02072-5.</Citation><ArticleIdList><ArticleId IdType="doi">10.1186/s12939-023-02072-5</ArticleId><ArticleId IdType="pmc">PMC10717295</ArticleId><ArticleId IdType="pubmed">38093291</ArticleId></ArticleIdList></Reference><Reference><Citation>Khullar D, Zhang Y, Zang C, et al. Racial/Ethnic Disparities in Post-acute Sequelae of SARS-CoV-2 Infection in New York: an EHR-Based Cohort Study from the RECOVER Program. J Gen Intern Med. 2023;38:1127&#x2013;36. doi: 10.1007/s11606-022-07997-1.</Citation><ArticleIdList><ArticleId IdType="doi">10.1007/s11606-022-07997-1</ArticleId><ArticleId IdType="pmc">PMC9933823</ArticleId><ArticleId IdType="pubmed">36795327</ArticleId></ArticleIdList></Reference><Reference><Citation>Kingstone T, Taylor AK, O&#x2019;Donnell CA, et al. Finding the &#x201c;right&#x201d; GP: a qualitative study of the experiences of people with Long-COVID. BJGP Open. 2020;4:bjgpopen20X101143. doi: 10.3399/bjgpopen20X101143.</Citation><ArticleIdList><ArticleId IdType="doi">10.3399/bjgpopen20X101143</ArticleId><ArticleId IdType="pmc">PMC7880173</ArticleId><ArticleId IdType="pubmed">33051223</ArticleId></ArticleIdList></Reference><Reference><Citation>Hung P, Brehon K, Miciak M, et al. &#x201c;I Had to Know About It, I Had to Find It, I Had to Know How to Access it&#x201d;: Experiences of Access to Rehabilitation Services Among People Living with Long COVID. Physiother Can. 2024;76:8&#x2013;24. doi: 10.3138/ptc-2023-0021.</Citation><ArticleIdList><ArticleId IdType="doi">10.3138/ptc-2023-0021</ArticleId><ArticleId IdType="pmc">PMC10919370</ArticleId><ArticleId IdType="pubmed">38465303</ArticleId></ArticleIdList></Reference><Reference><Citation>Davenport TE, Stevens SR, Stevens S, et al. Lessons from myalgic encephalomyelitis/chronic fatigue syndrome for Long COVID: postexertional symptom exacerbation is an abnormal response to exercise/activity. JOSPT Blog; 2022.</Citation></Reference><Reference><Citation>Grach SL, Seltzer J, Chon TY, et al. Diagnosis and Management of Myalgic Encephalomyelitis/Chronic Fatigue Syndrome. Mayo Clin Proc. 2023;98:1544&#x2013;51. doi: 10.1016/j.mayocp.2023.07.032.</Citation><ArticleIdList><ArticleId IdType="doi">10.1016/j.mayocp.2023.07.032</ArticleId><ArticleId IdType="pubmed">37793728</ArticleId></ArticleIdList></Reference><Reference><Citation>Horlick S, Krysa JA, Brehon K, et al. Exploring Rehabilitation Provider Experiences of Providing Health Services for People Living with Long COVID in Alberta. Int J Environ Res Public Health. 2023;20:7176. doi: 10.3390/ijerph20247176.</Citation><ArticleIdList><ArticleId IdType="doi">10.3390/ijerph20247176</ArticleId><ArticleId IdType="pmc">PMC10743286</ArticleId><ArticleId IdType="pubmed">38131727</ArticleId></ArticleIdList></Reference><Reference><Citation>Toepfner N, Brinkmann F, Augustin S, et al. Long COVID in pediatrics-epidemiology, diagnosis, and management. Eur J Pediatr. 2024;183:1543&#x2013;53. doi: 10.1007/s00431-023-05360-y.</Citation><ArticleIdList><ArticleId IdType="doi">10.1007/s00431-023-05360-y</ArticleId><ArticleId IdType="pmc">PMC11001657</ArticleId><ArticleId IdType="pubmed">38279014</ArticleId></ArticleIdList></Reference><Reference><Citation>Seylanova N, Chernyavskaya A, Degtyareva N, et al. Core outcome measurement set for research and clinical practice in post-COVID-19 condition (long COVID) in children and young people: an international Delphi consensus study &#x201c;PC-COS Children.&#x201d;. Eur Respir J. 2024;63:2301761. doi: 10.1183/13993003.01761-2023.</Citation><ArticleIdList><ArticleId IdType="doi">10.1183/13993003.01761-2023</ArticleId><ArticleId IdType="pmc">PMC10938351</ArticleId><ArticleId IdType="pubmed">38359962</ArticleId></ArticleIdList></Reference></ReferenceList></PubmedData></PubmedArticle></PubmedArticleSet>